data_comparator/app.py
data_comparator/data_comparator.py
data_comparator/components/__init__.py
data_comparator/components/check.py
data_comparator/components/comparison.py
data_comparator/components/data_cupboard.py
data_comparator/components/dataset.py
data_comparator/components/validations_config.json
data_comparator/ui/__init__.py
data_comparator/ui/data_comparator.ui
data_comparator/ui_models/__init__.py
data_comparator/ui_models/buttons.py
data_comparator/ui_models/combo_boxes.py
data_comparator/ui_models/lists.py
data_comparator/ui_models/tables.py
data_comparator/ui_models/utilities.py
data_comparator-0.8.0.dist-info/LICENSE
data_comparator-0.8.0.dist-info/METADATA
data_comparator-0.8.0.dist-info/WHEEL
data_comparator-0.8.0.dist-info/entry_points.txt
data_comparator-0.8.0.dist-info/top_level.txt
data_comparator-0.8.0.dist-info/RECORD
