Metadata-Version: 2.1
Name: data-comparator
Version: 0.8.0
Summary: Data profiling tool with a focus on dataset comparisons
Home-page: https://github.com/culight/data_comparator
Author: Demerrick Moton
Author-email: dmoton3.14@gmail.com
Classifier: Programming Language :: Python :: 3
Classifier: License :: OSI Approved :: MIT License
Classifier: Operating System :: OS Independent
Requires-Python: >=3.6
License-File: LICENSE
